{
	"id": "{3DAF24B0-3002-3F1B-27D0-155FDE2BFE41}",
	"caption": "Send message to syslog",
	"form": [
		"return [",
		"  [",
		"    'type' => 'ValidationTextBox',",
		"    'name' => 'MESSAGE',",
		"    'caption' => 'Message',",
		"  ],",
		"  [",
		"    'type' => 'Select',",
		"    'name' => 'SEVERITY',",
		"    'caption' => 'Severity',",
		"    'options' => [",
		"       [",
		"         'value' => 'emergency',",
		"         'caption' => 'Emergency',",
		"       ],",
		"       [",
		"         'value' => 'alert',",
		"         'caption' => 'Alert',",
		"       ],",
		"       [",
		"         'value' => 'critical',",
		"         'caption' => 'Critical',",
		"       ],",
		"       [",
		"         'value' => 'error',",
		"         'caption' => 'Error',",
		"       ],",
		"       [",
		"         'value' => 'warning',",
		"         'caption' => 'Warning',",
		"       ],",
		"       [",
		"         'value' => 'notice',",
		"         'caption' => 'Notice',",
		"       ],",
		"       [",
		"         'value' => 'info',",
		"         'caption' => 'Information',",
		"       ],",
		"       [",
		"         'value' => 'debug',",
		"         'caption' => 'Debug',",
		"       ],",
		"     ],",
		"    'value' => IPS_GetProperty($_IPS['TARGET'], 'default_severity'),",
		"  ],",
		"  [",
		"    'type' => 'Select',",
		"    'name' => 'FACILITY',",
		"    'caption' => 'Facility',",
		"    'options' => [",
		"       [",
		"         'value' => 'auth',",
		"         'caption' => 'auth',",
		"       ],",
		"       [",
		"         'value' => 'local0',",
		"         'caption' => 'local0',",
		"       ],",
		"       [",
		"         'value' => 'local1',",
		"         'caption' => 'local1',",
		"       ],",
		"       [",
		"         'value' => 'local2',",
		"         'caption' => 'local2',",
		"       ],",
		"       [",
		"         'value' => 'local3',",
		"         'caption' => 'local3',",
		"       ],",
		"       [",
		"         'value' => 'local4',",
		"         'caption' => 'local4',",
		"       ],",
		"       [",
		"         'value' => 'local5',",
		"         'caption' => 'local5',",
		"       ],",
		"       [",
		"         'value' => 'local6',",
		"         'caption' => 'local6',",
		"       ],",
		"       [",
		"         'value' => 'local7',",
		"         'caption' => 'local7',",
		"       ],",
		"       [",
		"         'value' => 'user',",
		"         'caption' => 'user',",
		"       ],",
		"     ],",
		"    'value' => IPS_GetProperty($_IPS['TARGET'], 'default_facility'),",
		"  ],",
		"  [",
		"    'type' => 'ValidationTextBox',",
		"    'name' => 'PROGRAM',",
		"    'caption' => 'Program',",
		"    'value' => IPS_GetProperty($_IPS['TARGET'], 'default_program'),",
		"  ],",
	    "];"
	],
	"action": "Syslog_Message($_IPS['TARGET'], $_IPS['MESSAGE'], $_IPS['SEVERITY'], $_IPS['FACILITY'], $_IPS['PROGRAM']);",
	"restrictions": {
		"objectType": [
			1
		],
		"moduleID": [
			"{2D3D36C0-E7AC-4F4C-ACB7-D54D87011B0E}"
		],
		"includeEnvironments": [
			"TestCommands",
			"Default"
		]
	},
	"priority": 10,
	"category": "target",
	"format": "Send message to syslog with severity \"{SEVERITY}\", facility \"${FACILITY}\" and \"{MESSAGE}\"",
	"locale": {
		"de": {
			"Send message to syslog": "Nachricht an Syslog schicken",
			"Message": "Nachrichten-Text",
			"Severity": "Schweregrad",
			"Facility": "Kategorie",
			"Program": "Programm",
			"Send message to syslog with severity \"{SEVERITY}\", facility \"${FACILITY}\" and \"{MESSAGE}\"": "Nachricht an Syslog mit Schweregrad \"{SEVERITY}\", Einrichtung \"${FACILITY}\" und \"{MESSAGE}\" senden"
		}
	}
}
